volley_grids/misc/helpers.py
volley_grids/models/matches.py
volley_grids/models/players.py
volley_grids/models/teams.py
volley_grids/models/tournaments.py
volley_grids/seeders/base_seeder.py
volley_grids/seeders/challenge_24_teams.py
volley_grids/seeders/double_elimination.py
volley_grids/seeders/king_of_the_beach.py
volley_grids/seeders/round_robin.py
volley_grids/seeders/single_elimination.py
volley_grids-0.0.1a0.dist-info/LICENSE
volley_grids-0.0.1a0.dist-info/METADATA
volley_grids-0.0.1a0.dist-info/WHEEL
volley_grids-0.0.1a0.dist-info/top_level.txt
volley_grids-0.0.1a0.dist-info/RECORD
