Metadata-Version: 2.1
Name: volley-grids
Version: 0.0.1a0
Summary: Competition grids for volleyball tournaments
Author-email: Oleh Perlovskyi <mupastir@gmail.com>
Project-URL: Homepage, https://github.com/mupastir/volley-grids
Project-URL: Documentation, https://docs.volley-grids.dev
Project-URL: Funding, https://github.com/sponsors/mupastir
Project-URL: Source, https://github.com/mupastir/volley-grids
Project-URL: Changelog, https://docs.volley-grids.dev/latest/changelog/
Classifier: Development Status :: 3 - Alpha
Classifier: Programming Language :: Python
Classifier: Programming Language :: Python :: Implementation :: CPython
Classifier: Programming Language :: Python :: Implementation :: PyPy
Classifier: Programming Language :: Python :: 3
Classifier: Programming Language :: Python :: 3 :: Only
Classifier: Programming Language :: Python :: 3.8
Classifier: Programming Language :: Python :: 3.9
Classifier: Programming Language :: Python :: 3.10
Classifier: Programming Language :: Python :: 3.11
Classifier: Programming Language :: Python :: 3.12
Classifier: Intended Audience :: Developers
Classifier: Intended Audience :: Information Technology
Classifier: Intended Audience :: System Administrators
Classifier: License :: OSI Approved :: MIT License
Classifier: Operating System :: Unix
Classifier: Operating System :: POSIX :: Linux
Classifier: Environment :: Console
Classifier: Environment :: MacOS X
Classifier: Framework :: Hypothesis
Classifier: Framework :: Pydantic
Classifier: Topic :: Software Development :: Libraries :: Python Modules
Classifier: Topic :: Other/Nonlisted Topic
Requires-Python: >=3.11
License-File: LICENSE
Requires-Dist: pydantic ==2.6.3
